{
  "id": "-hhiLUFPjMM",
  "title": "スーパーの塩鮭がマジで化けます。絶対に常備すること確定、至高の塩鮭の調理法3品",
  "channel": "料理研究家リュウジのバズレシピ",
  "url": "https://www.youtube.com/watch?v=-hhiLUFPjMM",
  "thumbnail": "https://i.ytimg.com/vi/-hhiLUFPjMM/maxresdefault.jpg",
  "duration": "21:24",
  "duration_seconds": 1284,
  "upload_date": "20240409",
  "added_at": "2026-04-06",
  "tags": [
    "鮭",
    "作り置き"
  ],
  "view_count": null,
  "like_count": null,
  "description": "",
  "subtitles": {},
  "ingredients": [
    {
      "name": "【鮭フレーク】甘塩鮭",
      "amount": "250g"
    },
    {
      "name": "みりん",
      "amount": "大さじ1と1/2"
    },
    {
      "name": "酒",
      "amount": "大さじ3"
    },
    {
      "name": "塩",
      "amount": "1つまみ"
    },
    {
      "name": "サラダ油",
      "amount": "適量"
    },
    {
      "name": "【鮭だし茶漬け】ご飯",
      "amount": "200g"
    },
    {
      "name": "水",
      "amount": "200cc"
    },
    {
      "name": "鰹粉",
      "amount": "2g"
    },
    {
      "name": "塩",
      "amount": "2つまみ"
    },
    {
      "name": "味の素",
      "amount": "4振り"
    },
    {
      "name": "海苔・いりごま・わさび",
      "amount": "各適量"
    },
    {
      "name": "【鮭たまオムレツ】卵",
      "amount": "2個"
    },
    {
      "name": "長ネギ",
      "amount": "30g"
    },
    {
      "name": "「これ!うま!!つゆ」",
      "amount": "小さじ2"
    },
    {
      "name": "鮭フレーク（オムレツ用）",
      "amount": "大さじ2"
    },
    {
      "name": "【鮭マヨトースト】食パン",
      "amount": "1枚"
    },
    {
      "name": "マヨネーズ",
      "amount": "大さじ2"
    },
    {
      "name": "鮭フレーク（トースト用）",
      "amount": "大さじ2"
    }
  ],
  "steps": [
    {
      "step": 1,
      "text": "【鮭フレーク】フライパンにサラダ油を熱し、甘塩鮭250gを皮ごと両面焼く。皮を取り除き、みりん大さじ1と1/2・酒大さじ3・塩1つまみを加えて炒り煮にしながら身をほぐしてフレーク状にする",
      "point": "酒をたっぷり使うことで鮭の臭みが飛び、しっとりジューシーなフレークになる。みりんの甘みが旨みを引き立てる。冷蔵で1週間保存可能でいろいろな料理に使える。"
    },
    {
      "step": 2,
      "text": "【鮭だし茶漬け】鍋に水200cc・味の素4振り・鰹粉2g・塩2つまみを入れて沸かしてだし汁を作る。ご飯200gに鮭フレーク大さじ2〜3を乗せ、熱いだし汁をかけ、海苔・いりごま・わさびを添えて完成",
      "point": "自家製だし汁をかけることで本格的な茶漬けになる。わさびとの相性が抜群。鮭フレークが汁に溶け出して旨みたっぷりのスープになる。"
    },
    {
      "step": 3,
      "text": "【鮭たまオムレツ】卵2個・これ!うま!!つゆ小さじ2・塩1つまみ・長ネギ30gを混ぜ合わせ、鮭フレーク大さじ2を加えてフライパンで半熟オムレツに仕上げる。【鮭マヨトースト】食パンにマヨネーズ大さじ2・鮭フレーク大さじ2・黒胡椒を乗せてトーストするだけで完成",
      "point": "鮭フレークはオムレツや卵と相性が良く、ニラ玉ならぬ鮭玉風の一品になる。マヨトーストはマヨネーズの油分と鮭の旨みが合わさって絶品。どちらも鮭フレークがあれば5分で作れる。"
    }
  ]
}