{
  "id": "b9V4X-Vkk7c",
  "title": "僕が昔働いていた超人気レストランで一番人気だった伝説のパスタの作り方【真夜中のパスタ】",
  "channel": "料理研究家リュウジのバズレシピ",
  "url": "https://www.youtube.com/watch?v=b9V4X-Vkk7c",
  "thumbnail": "https://i.ytimg.com/vi/b9V4X-Vkk7c/sddefault.jpg",
  "duration": "13:43",
  "duration_seconds": 823,
  "upload_date": "2022-03-21",
  "added_at": "2026-04-07",
  "view_count": 1583471,
  "like_count": 20285,
  "tags": [
    "シーフードパスタ",
    "スパイシー",
    "トマトパスタ",
    "パスタ",
    "バズレシピ",
    "リュウジ"
  ],
  "description": "動画を見ていただいて楽しんで頂けましたら\n高評価、コメントをお願いします！\n\n【真夜中のパスタ】\n是非お試しください！",
  "ingredients": [
    {
      "name": "パスタ（1.4mm）",
      "amount": "100g"
    },
    {
      "name": "シーフードミックス",
      "amount": "70g"
    },
    {
      "name": "ベーコン",
      "amount": "30g"
    },
    {
      "name": "トマト缶",
      "amount": "1/2缶"
    },
    {
      "name": "玉葱",
      "amount": "1/4個（60g）"
    },
    {
      "name": "マッシュルーム",
      "amount": "30g（あれば）"
    },
    {
      "name": "にんにく",
      "amount": "2片"
    },
    {
      "name": "水",
      "amount": "240cc"
    },
    {
      "name": "コンソメ",
      "amount": "小さじ2"
    },
    {
      "name": "パプリカパウダー",
      "amount": "小さじ1"
    },
    {
      "name": "一味唐辛子",
      "amount": "小さじ1/2"
    },
    {
      "name": "バジル",
      "amount": "小さじ1/2"
    },
    {
      "name": "オリーブオイル",
      "amount": "大さじ1＋仕上げ"
    },
    {
      "name": "塩・黒胡椒",
      "amount": "各適量"
    }
  ],
  "steps": [
    {
      "step": 1,
      "text": "オリーブオイル大さじ1でベーコン30g、玉葱60g、マッシュルーム30gを炒め、トマト缶1/2缶を加えてよく炒める。",
      "point": "トマト缶を入れてから炒めることで水分を飛ばしながら旨味を凝縮させる。ベーコンの脂がソースのコクになる。"
    },
    {
      "step": 2,
      "text": "水240cc、コンソメ小さじ2、パプリカパウダー小さじ1、一味唐辛子小さじ1/2、バジル小さじ1/2、塩、黒胡椒を加えて沸かす。",
      "point": "パプリカパウダーが赤みと甘みを、一味が辛みをプラスする。このスパイスの組み合わせがこのパスタの個性を作り出す。"
    },
    {
      "step": 3,
      "text": "シーフードミックス70gを加え、固めに茹でたパスタ100gとおろしにんにく2片を入れて仕上げオイルで完成。",
      "point": "パスタを固めに茹でることでソースと絡めながら火を入れる時間を確保できる。生にんにくを最後に加えることで香りが際立つ。"
    }
  ],
  "subtitles": {}
}