{
  "id": "Cfozon5Kb9s",
  "title": "シェフが即興で作る【ペペロンチーノ】どんなキノコでも絶対うまい！出汁を吸わせたパスタ",
  "channel": "ファビオ飯 /イタリア料理人の世界",
  "url": "https://www.youtube.com/watch?v=Cfozon5Kb9s",
  "thumbnail": "https://i.ytimg.com/vi/Cfozon5Kb9s/maxresdefault.jpg",
  "duration": "9:35",
  "duration_seconds": 575,
  "upload_date": "2022-12-19",
  "added_at": "2026-04-07",
  "tags": [
    "キノコパスタ",
    "ペペロンチーノ",
    "きのこ",
    "茹で汁",
    "魚醤",
    "賄いパスタ",
    "ファビオ飯",
    "アーリオオーリオ"
  ],
  "view_count": 268043,
  "like_count": 3922,
  "description": "季節のキノコを使った間違えないアーリオオーリオ🍝茹で汁でじっくりと煮てキノコの旨味をしっかりと吸わせたパスタの美味しさは最高です🤤\n\nーーーーーーーーーーーーーー\n◆関連動画◆\n革命！【ナポリタン2.0】激務の中生まれた料理人の賄いパスタ\nhttps://youtu.be/5mV6bs3iFMM\n\n怒涛のワンオペ厨房密着【コース料理】シェフがやっと到達した職人芸｜企業秘密の仕込編\nhttps://youtu.be/4yoZuDQpyqI\n\n怒涛の15人前【リアル厨房】コース料理ができるまで密着撮影\nhttps://youtu.be/rlrkGAne3xo\n\nーーーーーーーーーーーーーー\n材料1人前\nキタッラ　70g \nお好みのキノコ　80g\nニンニク　ひとかけ\n唐辛子　1/2本　\nイタリアンパセリ　4g\n塩　適量\nEXオリーブオイル　大2\n茹で汁　大1\n魚醤　適量\n\n作り方\n①湯に対して1%の塩を加えたパスタ湯でスパゲッティーニを8分茹で始める。\n②フライパンにEXオリーブ油、ニンニク、唐辛子のみじん切りをじっくり加熱キノコを炒める。\n③茹で汁を加えしばらく炊いて味見をし魚醤で味を整える。\n④茹で上げたパスタとイタパセを加え盛り付け完成です。\n\nーーーーーーーーーーーーーー\n◆今日のおすすめ食材◆\nアイコノEXオリーブオイル　https://amzn.to/3V5Ue03\nマンチーニ社　キタッラ　https://amzn.to/3hBHdNe\nクリスマス島の海の塩　https://amzn.to/3ElVG7C\nカラブリア唐辛子　https://a.r10.to/h5yxYN\n鮎の魚醤　https://amzn.to/3hAMQeF\n\n◆愛用機材◆　\nアルミフライパン 24cm    https://amzn.to/3tWiEgB\n貝印 KAI SELECT 100 ミニトング　https://amzn.to/3BdvmvB\nドレッジ　https://amzn.to/3d5FOMS\nゴムベラ　https://amzn.to/3L2phFX\n\nーーーーーーーーーーーーーーー\n📚ファビオのレシピ本📚\n【１冊目 】パスタと出汁に特化したパスタの本🍝\n→　https://amzn.to/3xcNDHa\n「出汁と素材の味を最大限に引き出す ファビオのとっておきパスタ」\n\n【２冊目】ワンランク上の味になる家庭料理本🍛\n→　https://amzn.to/3AYmQQ8\n「自分史上最高に美味しくできる ファビオ式定番おうちごはん」\n\n【３冊目】肉の火入れに特化した肉料理の本🥩🆕最新書籍！\n→　https://amzn.to/3B9P5eG\n「火入れを極めるファビオの肉料理」\n\nーーーーーーーーーーーーーーーーーーー\n◆Instagram　https://www.instagram.com/fabilog0016/\n◆Twitter   https://twitter.com/fabico0101\n◆TikTok　https://www.tiktok.com/@fabico02\n\n⬇︎⬇︎お仕事、案件、食材提供、コラボのご依頼はこちら🤝✨\nfabi030016@gmail.com\n\nーーーーーーーーーーーーーーーーーーー\n#パスタ #ペペロンチーノ #きのこパスタ",
  "ingredients": [
    {
      "name": "キタッラ（またはスパゲッティ）",
      "amount": "70g"
    },
    {
      "name": "お好みのきのこ",
      "amount": "80g"
    },
    {
      "name": "ニンニク",
      "amount": "1かけ"
    },
    {
      "name": "唐辛子",
      "amount": "1/2本"
    },
    {
      "name": "イタリアンパセリ",
      "amount": "4g"
    },
    {
      "name": "EXオリーブオイル",
      "amount": "大さじ2"
    },
    {
      "name": "茹で汁",
      "amount": "大さじ1"
    },
    {
      "name": "魚醤",
      "amount": "適量"
    }
  ],
  "steps": [
    {
      "step": 1,
      "text": "きのこをほぐし、ニンニクとパセリをみじん切りにする。フライパンにオリーブオイルとニンニク、唐辛子を加えて弱火で香りを立てる。",
      "point": "きのこは手でほぐすことで断面が不規則になりソースが絡みやすくなる。ペペロンチーノのベースは弱火でじっくり作ること。このアーリオオーリオベースがきのこの旨味を最大限に活かす土台になる。"
    },
    {
      "step": 2,
      "text": "きのこを加えて中火でしっかり焼き色をつける。きのこから水分が出てきたら蒸発させながら炒め続ける。",
      "point": "きのこはしっかり焼き色をつけることで旨味が凝縮する。水分が出てきても蒸発させながら炒めることで旨味が詰まっていく。焼き色がついたきのこは格段に美味しくなる。"
    },
    {
      "step": 3,
      "text": "茹で汁を加えてソースとし、魚醤を数滴垂らして旨味を底上げする。茹で上がったパスタを加えて絡める。",
      "point": "茹で汁ときのこの旨味が合わさって凝縮したブロードになる。魚醤を少量加えることでうま味が増幅され、シンプルなきのこパスタが格上がりする。少量でも効果絶大なのが魚醤の力。"
    },
    {
      "step": 4,
      "text": "パセリを加えてさっと和え、仕上げにオリーブオイルを垂らして完成。",
      "point": "パセリは最後に加えて香りを活かす。仕上げのオリーブオイルが全体に艶とコクを与える。どんなきのこでも間違えない絶品ペペロンチーノが10分以内で完成する。"
    }
  ],
  "subtitles": {
    "ja": "でここで軽くこう\n煮てあげて\n[拍手]\nはいこんにちはシェフのファビューです今\n中央にいるのでこれからまかない作って\nいこうと思うんですけど今日は\n定番のアリオールをペペロンチーノベース\nでちょっと季節も秋っていうことでキノコ\nのペペロンチーノを作っていきます\nで今あのちょうど\n仕事でこれ使うやつなんですけど\n端数でこれカルドンチェルドって言って\nちょっとイタリアの高級キノコですねこれ\nは日本のエリンギンに似たような感じで\nあるんですけどエリンギよりはもう\nちょっとあの上品で\n繊細なキノコですなので皆さんやるときは\n全然エリンギで\n代用していただいて大丈夫ですこれは\nちょっともう掃除した状態\n軽くこう水で洗ってすぐ拭いた状態ですね\nでキノコはこう切ると\n切るときに全部やらないでこう手でこう\n裂くと\nこういうふうになるのででせっかくいい\nキノコなので\n半割4分の1カットぐらいにしていきます\nでニンニクはあの今日は\n注射にんにくにしていくので一度国産の\nものを使っていきますで今日2人前作って\nいくので\n2かけ分\n芯が中に入ってるんで\n半分にしてから\n潰しますでキノコのペペロンチーノは結構\nキノコの出汁の旨味とか\n香りがすごく大事な\nペペロンチーノになるので僕は結構潰す\nやり方が多いですねで\n潰したニンニクはフライパンに出てきます\nで2掛分ですね\nニンニク入ったんで\nオリーブオイル2人前ですねでこう傾けた\n時に\nこれニンニクが軽く出るぐらいこれぐらい\nの量です\nでここにアリオーリオなので\n空振りは唐辛子して砕いてこんな感じで\nはいこれで\nでパスタ茹でる茹でるところに\n塩を入れていくんですけど\n今日はですねちょっと茹で汁も入るような\nパスタになってくるので\nちょうど1%ぐらい\nちょうど1%ぐらい入れていきます\nであのこういう粒のあの大きい塩を入れる\n時は\n少し何分か待たないと塩が溶けた状態に\nならないので少し待ってから\n味見して\n麺を茹でていきますで塩が溶けたので目\n茹でていくんですけど今日はちょっと\n僕の気分なんですけどやっていきます\n北浦は断面が四角いパスタなのでちょっと\n食べた時に\n食感が面白いとか四角いのでなんか\nカクカクしたような食感がするので\nキノコ系とか\nラグー系とかに汚いよく使ったりしますで\n来たら10分ぐらいかかるので最初にやっ\nてから\nソース作っていきます\nではオイルの方も\n加熱始めます\nまずはちょっとある程度\nオリーブオイルのこの温度上げてあげて\nニンニクがフツフツする状態に持っていき\nますちょっとふつふつしてきたら\n弱くしますで今この外側がやっぱり厚く\nなって温度が上がってるので中がちょっと\n低いんですよそしてちょっとだけこう\n揺すってあげる\n揺すってからこれまたキープにんにくの\n香りを出している間に\nイタリアンパセリを\n切りますやっぱりどんな\nペペロンチーノを作るにしてもやっぱり\n板橋はたっぷり入った方が美味しいので\n板パスがない場合はパセリでやっても\n大丈夫であるんですけどやっぱり\nイタリアンパセリの方が\n芳賀柔らかいのでたっぷり入れると\n美味しいですね\nそしたら\n今だいぶ\nにんにくの\n香りが立ってきたので\n色が気持ち乗ってきた状態ここまでしたら\nもうニンニクに今火が入ってるので\nここで\nキノコが入ります\nでこの\nニンニクオイルをまずあのキノコに\nなじませる\n全体になじませます\n最初は今これ弱火なんですけどじっくりと\nこのカルトンチェロに焼き色をつけてあげ\nるっていう仕事ですねでここでだいたい\nソースやるときに最初に塩\nちゃうんですけど\n使用するともう水分がどんどんキノコから\n出ちゃうのでまずは焼き色をつけてで最後\nに塩をするということをすると\n焼き色もつくし\nキノコの状態がいい状態ですねで\nでカルドンチェロに焼き色がついてきたの\nでここで塩\n軽く\nそしたらまたちょっと\n回してあげる\nで茹で汁を\n入れます\nここで軽くこう\nこのカルトンチェロのうま味をこのソース\nに溶け込ましてあげるイメージで\nでここで今ベースができたので1回味見を\nします\n美味しいですねで今あのとろ火でちょっと\n似てる状態なんですけどさらに旨味を\nちょっと\n鮎の化粧を\n少量本当に\nで魚醤は\nコラトゥーラーとか\n使ってもいいんですけど\n鮎の魚醤はですねあの\n結構量入れても\n塩味が\n柔らかいので大丈夫なんですけど普通の\n魚醤入れる時は\n量すごい鉛筆良かったりするので\n気をつけてください\n味見しながらですねで今この\n鍋の中のフライパンの中のキノコの状態な\nんですけどまあ焼き色は軽くついてて\nみずみずしい状態でカルドンチェローって\n結構ジューシーなキノコなので\n焼き目はつけるんですけど\n水分飛ばしすぎないっていうのがこの\nペペロンチーノの作り方ですねこれは\nシェフによっても\nキノコの水分をしっかりオーブンで飛ばし\nたやつを\n入れる方もいればこうやって重心にする方\nもいるので本当に好みの作り方ですねで\nあのだいたい10分ぐらいかかるんです\nけど麺はこう23回混ぜてあげると\nくっつかないでいい状態入れられるので\nたまに混ぜてあげます\nはいそれでは面が良かったので合わせてき\nます\nで合わせます\nで麺はちょっと1分前ぐらいに\n気持ち硬めに上げたのでこの\nソースの中で1分ぐらい吸わせてあげる\nイメージですねでパセリ入ります\nでこう傾けた時にこのトロっとした\nソースがある状態ですね\nはいそれではいい感じに絡んだメモリ\n付き合います\nでカルドンチェロのペペロンチーノ完成\nです\nでは早速熱いうちにいただきます\n今日はちょっと珍しく来たらを使ってやっ\nたんですけどやっぱりあのこういう\nちょっと食感があるパスタってあの\nイタリアとかも結構\n太麺でやることが多いんですけど\n来たらもう結構茹で時間かかるので\n食感がやっぱりあるんですよねだから\nペペロンチーノとか今日はキノコ入りまし\nたけどシンプルなパスタほどこういう\nなんか\n太麺使った方がパスタ食べて\nるっていうような感じになりますねはい\nごちそうさまです\nこの体茶色のペペロンチーノなんですけど\nもちろんエリンギでやってもすごく\n美味しくできるので良かったら作ってみて\nくださいはいいつもコメントありがとう\nございます\n楽しみに拝見させていただいてますはい\nそれではまた次回の動画でお会いし\nましょうじゃあねー\n[音楽]"
  }
}