{
  "id": "QT4xyprfb5A",
  "title": "もう二度とパスタ茹でないわこれ。1皿９８円、貧乏を助けるやけくそトマトパスタ",
  "channel": "料理研究家リュウジのバズレシピ",
  "url": "https://www.youtube.com/watch?v=QT4xyprfb5A",
  "thumbnail": "https://i.ytimg.com/vi/QT4xyprfb5A/maxresdefault.jpg",
  "duration": "21:34",
  "duration_seconds": 1294,
  "upload_date": "2025-05-14",
  "added_at": "2026-04-07",
  "view_count": 770063,
  "like_count": 9804,
  "tags": [
    "パスタ",
    "トマト",
    "レンジレシピ",
    "節約",
    "リュウジ",
    "バズレシピ"
  ],
  "description": "",
  "subtitles": {},
  "ingredients": [
    {
      "name": "1.5mmのパスタ",
      "amount": "100g"
    },
    {
      "name": "トマトジュース",
      "amount": "100cc"
    },
    {
      "name": "水",
      "amount": "220cc"
    },
    {
      "name": "ガーリックパウダー",
      "amount": "7振り"
    },
    {
      "name": "こんぶだし",
      "amount": "小さじ1"
    },
    {
      "name": "塩",
      "amount": "小さじ1/3"
    },
    {
      "name": "一味唐辛子",
      "amount": "4振り"
    },
    {
      "name": "砂糖",
      "amount": "1つまみ"
    },
    {
      "name": "オリーブオイル",
      "amount": "大さじ1"
    }
  ],
  "steps": [
    {
      "step": 1,
      "text": "耐熱容器にパスタ100g・水220cc・トマトジュース100cc・ガーリックパウダー7振り・昆布だし小さじ1・塩小さじ1/3・一味4振り・砂糖1つまみ・オリーブオイル大さじ1を入れ、ラップをせず600Wのレンジで10分加熱",
      "point": "トマトジュースを直接調理液に使うことでトマトの旨みがパスタに染み込む。昆布だしとガーリックパウダーの組み合わせが本格的な旨みを作る。1皿98円の節約レシピなのに驚くほど旨い。"
    },
    {
      "step": 2,
      "text": "仕上げにオリーブオイル小さじ1をかけて完成。好みでマジスコをかけて味変",
      "point": "仕上げのオリーブオイルで香りと艶が加わり一気にレベルアップ。火を使わないレンジだけで作れる手軽さが「もう二度とパスタを茹でない」と言わしめる理由。"
    }
  ]
}