{
  "id": "z7rGZ1tGq6s",
  "title": "市販のルーがガチで高級レストランレベルになる究極のチーズシチュー",
  "channel": "料理研究家リュウジのバズレシピ",
  "url": "https://www.youtube.com/watch?v=z7rGZ1tGq6s",
  "thumbnail": "https://i.ytimg.com/vi/z7rGZ1tGq6s/sddefault.jpg",
  "duration": "13:30",
  "duration_seconds": 810,
  "upload_date": "2022-10-30",
  "added_at": "2026-04-07",
  "tags": [
    "シチュー",
    "チーズ",
    "鶏もも肉",
    "市販ルー",
    "バズレシピ",
    "リュウジ"
  ],
  "view_count": 2094472,
  "like_count": 23430,
  "description": "",
  "subtitles": {},
  "ingredients": [
    {
      "name": "バター",
      "amount": "10g"
    },
    {
      "name": "塩コショウ",
      "amount": "適量"
    },
    {
      "name": "鶏もも肉",
      "amount": "350g"
    },
    {
      "name": "じゃがいも",
      "amount": "150g"
    },
    {
      "name": "にんじん",
      "amount": "150g"
    },
    {
      "name": "玉葱",
      "amount": "250g"
    },
    {
      "name": "水",
      "amount": "400cc"
    },
    {
      "name": "牛乳",
      "amount": "200cc"
    },
    {
      "name": "シチュールー",
      "amount": "半箱"
    },
    {
      "name": "ピザチーズ",
      "amount": "70g"
    },
    {
      "name": "黒胡椒",
      "amount": "適量"
    }
  ],
  "steps": [
    {
      "step": 1,
      "text": "バター10gで塩コショウした鶏もも肉350g（一口大）を炒め、じゃがいも150g・にんじん150g・玉葱250gを加えて炒める。",
      "point": "バターで鶏肉に焼き色をつけることで香ばしさが増す。野菜も軽く炒めることで旨みが凝縮される。"
    },
    {
      "step": 2,
      "text": "水400cc・牛乳200ccを入れて蓋をして20分煮込む。",
      "point": "牛乳を入れることでまろやかなシチューのベースができる。水と牛乳の比率を守ることでルーの溶け加減がちょうどよくなる。"
    },
    {
      "step": 3,
      "text": "火を弱めてシチュールー半箱を溶かし、ピザチーズ70g・黒胡椒を加えて完成。タバスコで味変もおすすめ。",
      "point": "チーズを加えることで高級感が増し市販ルーとは思えない仕上がりになる。ルーを入れる前に弱火にすることでダマになりにくい。"
    }
  ]
}